<?xml version="1.0" encoding="UTF-8"?>
<databaseChangeLog
    xmlns="http://www.liquibase.org/xml/ns/dbchangelog"
    xmlns:xsi="http://www.w3.org/2001/XMLSchema-instance"
    xsi:schemaLocation="http://www.liquibase.org/xml/ns/dbchangelog
    http://www.liquibase.org/xml/ns/dbchangelog/dbchangelog-3.8.xsd">

    <changeSet id="lab-unit-001-create-lab-unit-table" author="ogc-189-feature">
        <preConditions onFail="MARK_RAN">
            <not>
                <tableExists tableName="lab_unit"/>
            </not>
        </preConditions>
        <createTable tableName="lab_unit">
            <column name="id" type="VARCHAR(36)">
                <constraints primaryKey="true" nullable="false"/>
            </column>
            <column name="name" type="VARCHAR(100)">
                <constraints nullable="false"/>
            </column>
            <column name="code" type="VARCHAR(50)"/>
            <column name="description" type="VARCHAR(500)"/>
            <column name="organization_id" type="VARCHAR(36)"/>
            <column name="parent_lab_unit_id" type="VARCHAR(36)"/>
            <column name="sort_order" type="numeric(10,0)"/>
            <column name="is_active" type="VARCHAR(1)" defaultValue="Y">
                <constraints nullable="false"/>
            </column>
            <column name="fhir_uuid" type="UUID">
                <constraints unique="true"/>
            </column>
            <column name="sys_user_id" type="VARCHAR(36)"/>
            <column name="lastupdated" type="TIMESTAMP"/>
        </createTable>
        
        <addForeignKeyConstraint 
            baseTableName="lab_unit" 
            baseColumnNames="organization_id"
            referencedTableName="organization"
            referencedColumnNames="id"
            constraintName="fk_lab_unit_organization"
            onDelete="SET NULL"/>
        
        <addForeignKeyConstraint 
            baseTableName="lab_unit" 
            baseColumnNames="parent_lab_unit_id"
            referencedTableName="lab_unit"
            referencedColumnNames="id"
            constraintName="fk_lab_unit_parent"
            onDelete="SET NULL"/>
        
        <rollback>
            <dropTable tableName="lab_unit"/>
        </rollback>
    </changeSet>

    <changeSet id="lab-unit-002-create-lab-unit-assignment-table" author="ogc-189-feature">
        <preConditions onFail="MARK_RAN">
            <not>
                <tableExists tableName="lab_unit_assignment"/>
            </not>
        </preConditions>
        <createTable tableName="lab_unit_assignment">
            <column name="id" type="numeric(10,0)">
                <constraints primaryKey="true" nullable="false"/>
            </column>
            <column name="lab_unit_id" type="VARCHAR(36)">
                <constraints nullable="false"/>
            </column>
            <column name="assignment_type" type="VARCHAR(20)">
                <constraints nullable="false"/>
            </column>
            <column name="assigned_item_id" type="VARCHAR(36)">
                <constraints nullable="false"/>
            </column>
            <column name="assigned_date" type="TIMESTAMP"/>
            <column name="sys_user_id" type="VARCHAR(36)"/>
        </createTable>
        
        <createSequence sequenceName="lab_unit_assignment_seq" startValue="1" incrementBy="1"/>
        
        <addForeignKeyConstraint 
            baseTableName="lab_unit_assignment" 
            baseColumnNames="lab_unit_id"
            referencedTableName="lab_unit"
            referencedColumnNames="id"
            constraintName="fk_assignment_lab_unit"
            onDelete="CASCADE"/>
        
        <rollback>
            <dropSequence sequenceName="lab_unit_assignment_seq"/>
            <dropTable tableName="lab_unit_assignment"/>
        </rollback>
    </changeSet>

    <changeSet id="lab-unit-003-create-indexes" author="ogc-189-feature">
        <preConditions onFail="MARK_RAN">
            <not>
                <indexExists tableName="lab_unit" indexName="idx_lab_unit_organization"/>
            </not>
        </preConditions>
        <createIndex tableName="lab_unit" indexName="idx_lab_unit_organization">
            <column name="organization_id"/>
        </createIndex>
        
        <createIndex tableName="lab_unit" indexName="idx_lab_unit_parent">
            <column name="parent_lab_unit_id"/>
        </createIndex>
        
        <createIndex tableName="lab_unit_assignment" indexName="idx_assignment_type">
            <column name="assignment_type"/>
        </createIndex>
        
        <createIndex tableName="lab_unit_assignment" indexName="idx_assignment_item">
            <column name="assigned_item_id"/>
        </createIndex>
        
        <rollback>
            <dropIndex tableName="lab_unit" indexName="idx_lab_unit_organization"/>
            <dropIndex tableName="lab_unit" indexName="idx_lab_unit_parent"/>
            <dropIndex tableName="lab_unit_assignment" indexName="idx_assignment_type"/>
            <dropIndex tableName="lab_unit_assignment" indexName="idx_assignment_item"/>
        </rollback>
    </changeSet>

    <changeSet id="lab-unit-004-insert-initial-data" author="ogc-189-feature">
        <preConditions onFail="MARK_RAN">
            <sqlCheck expectedResult="0">SELECT COUNT(*) FROM lab_unit</sqlCheck>
        </preConditions>
        <insert tableName="lab_unit">
            <column name="id" value="ROOT-LAB-UNIT"/>
            <column name="name" value="Main Laboratory"/>
            <column name="is_active" value="Y"/>
            <column name="sys_user_id" value="1"/>
        </insert>
        
        <rollback>
            <delete tableName="lab_unit">
                <where>id = 'ROOT-LAB-UNIT'</where>
            </delete>
        </rollback>
    </changeSet>

</databaseChangeLog>